preprocessing/__init__.py
preprocessing/example.py
test_package_mlops-0.1.0.dist-info/METADATA
test_package_mlops-0.1.0.dist-info/WHEEL
test_package_mlops-0.1.0.dist-info/top_level.txt
test_package_mlops-0.1.0.dist-info/RECORD
