Metadata-Version: 2.1
Name: test-package-mlops
Version: 0.1.0
Summary: Preprocessing package
Author: Ivan
Author-email: ivan.kuis@innowise-group.com
Classifier: Topic :: Scientific/Engineering
Classifier: Programming Language :: Python
Requires-Python: >=3.8
Requires-Dist: numpy
Requires-Dist: pandas
Requires-Dist: matplotlib
Requires-Dist: importlib-metadata ; python_version < "3.8"
